{
    "providers": [
        {
            "type": "bitmap",
            "file": "space:font/ship_atlas.png",
            "ascent": 0,
            "height": 16,
            "chars": [
                "ABCDEFGHIJKLMNOP",
                "QRSTUVWXYZabcdef",
                "ghijklmnopqrstuv",
                "wxyz0123456789!?"
            ]
        },
        {
            "type": "bitmap",
            "file": "space:font/blank.png",
            "ascent": 0,
            "height": 0,
            "chars": [
                "_"
            ]
        }
    ]
}